camiba/__init__.py
camiba/data.py
camiba/algs/__init__.py
camiba/algs/admm.py
camiba/algs/esprit.py
camiba/algs/iht.py
camiba/algs/irls.py
camiba/algs/ista.py
camiba/algs/omp.py
camiba/cs/__init__.py
camiba/cs/scenario.py
camiba/cs/soe.py
camiba/linalg/__init__.py
camiba/linalg/basic.py
camiba/linalg/multilevel.py
camiba/linalg/pack.py
camiba/linalg/vand.py
camiba-0.1.1.dist-info/DESCRIPTION.rst
camiba-0.1.1.dist-info/METADATA
camiba-0.1.1.dist-info/RECORD
camiba-0.1.1.dist-info/WHEEL
camiba-0.1.1.dist-info/metadata.json
camiba-0.1.1.dist-info/top_level.txt
