Metadata-Version: 2.0
Name: camiba
Version: 0.1.1
Summary: Compressed Sensing Algorithms for Python
Home-page: https://github.com/SebastianSemper/camiba
Author: Sebastian Semper
Author-email: sebastian.semper@tu-ilmenau.de
License: LGPL3
Project-URL: Documentation, https://sebastiansemper.github.io/camiba/
Project-URL: Funding, https://www.tu-ilmenau.de/it-ems/
Project-URL: Say Thanks!, https://www.tu-ilmenau.de/it-ems/
Project-URL: Source, https://github.com/sebastiansemper/camiba
Project-URL: Tracker, https://github.com/sebastiansemper/camiba/issues
Platform: UNKNOWN
Classifier: Development Status :: 3 - Alpha
Classifier: Intended Audience :: Developers
Classifier: License :: OSI Approved :: GNU General Public License (GPL)
Classifier: Programming Language :: Python :: 3
Requires-Python: >=3
Requires-Dist: numpy
Requires-Dist: sphinx
Requires-Dist: scipy
Requires-Dist: numpydoc
